kci/__init__.py
kci/pointcloudviewer/.gitignore
kci/pointcloudviewer/__init__.py
kci/pointcloudviewer/__main__.py
kci/pointcloudviewer/_internal/.gitignore
kci/pointcloudviewer/_internal/__init__.py
kci/pointcloudviewer/_internal/down_sample.py
kci/pointcloudviewer/_internal/members/__init__.py
kci/pointcloudviewer/_internal/members/camera.py
kci/pointcloudviewer/_internal/members/capture_screen.py
kci/pointcloudviewer/_internal/members/custom_control.py
kci/pointcloudviewer/_internal/members/event_handler.py
kci/pointcloudviewer/_internal/members/internal_utils.py
kci/pointcloudviewer/_internal/members/keyboard_event_handler.py
kci/pointcloudviewer/_internal/members/remove_object.py
kci/pointcloudviewer/_internal/members/send_object.py
kci/pointcloudviewer/_internal/members/set_custom_control.py
kci/pointcloudviewer/_internal/members/utils.py
kci/pointcloudviewer/_internal/protobuf/__init__.py
kci/pointcloudviewer/_internal/protobuf/client_pb2.py
kci/pointcloudviewer/_internal/protobuf/server_pb2.py
kci/pointcloudviewer/_internal/server.py
kci/pointcloudviewer/_vendor/pypcd/LICENSE
kci/pointcloudviewer/_vendor/pypcd/pypcd.py
kci/pointcloudviewer/keyboard_event.py
kci/pointcloudviewer/pointcloudviewer.py
kci/pointcloudviewer/public/bundle.js
kci/pointcloudviewer/public/bundle.js.LICENSE.txt
kci/pointcloudviewer/public/bundle.js.map
kci/pointcloudviewer/public/index.html
kci/pointcloudviewer/public/main.css
kci/pointcloudviewer/public/main.css.map
kci.pointcloudviewer-0.19.1.dist-info/WHEEL
kci.pointcloudviewer-0.19.1.dist-info/METADATA
kci.pointcloudviewer-0.19.1.dist-info/RECORD
