Metadata-Version: 2.1
Name: kci.pointcloudviewer
Version: 0.19.1
Summary: Webブラウザ上に点群を描画する python ライブラリ
Home-page: https://github.com/kurusugawa-computer/pointcloud-viewer
License: BSD
Keywords: point-cloud,pcd
Author: Kurusugawa Computer
Requires-Python: >=3.7,<3.9
Classifier: Development Status :: 3 - Alpha
Classifier: Intended Audience :: Developers
Classifier: License :: OSI Approved :: BSD License
Classifier: License :: Other/Proprietary License
Classifier: Operating System :: OS Independent
Classifier: Programming Language :: Python
Classifier: Programming Language :: Python :: 3
Classifier: Programming Language :: Python :: 3 :: Only
Classifier: Programming Language :: Python :: 3.7
Classifier: Programming Language :: Python :: 3.8
Classifier: Topic :: Utilities
Requires-Dist: Pillow (>=9.0.1,<10.0.0)
Requires-Dist: numpy (>=1.20.2,<2.0.0)
Requires-Dist: protobuf (>=3.15.6,<4.0.0)
Requires-Dist: python-lzf (>=0.2.4,<0.3.0)
Requires-Dist: websockets (>=8.1,<9.0)
Project-URL: Repository, https://github.com/kurusugawa-computer/pointcloud-viewer
